beanycro/__init__.py
beanycro/logging.conf
beanycro/logging_setup.py
beanycro/test/__init__.py
beanycro/test/test.py
beanycro/test/test2/__init__.py
beanycro/test/test2/tmp.py
beanycro-0.0.1.dist-info/METADATA
beanycro-0.0.1.dist-info/WHEEL
beanycro-0.0.1.dist-info/licenses/LICENSE
beanycro-0.0.1.dist-info/RECORD
