Metadata-Version: 2.4
Name: beanycro
Version: 0.0.1
Summary: A package of utilities used for personal projects.
Project-URL: Homepage, https://github.com/Benicol/Beanycro
Project-URL: Issues, https://github.com/Benicol/Beanycro/issues
Author-email: Benjamin Nicol <benji.locin@gmail.com>
License-Expression: MIT
License-File: LICENSE
Classifier: Operating System :: OS Independent
Classifier: Programming Language :: Python :: 3
Requires-Python: >=3.13
